osnap_client/README.md
osnap_client/SwarmAdapters/BaseSwarmAdapter.py
osnap_client/SwarmAdapters/DiscordSwarmAdapter.py
osnap_client/SwarmAdapters/__init__.py
osnap_client/__init__.py
osnap_client/agents/OutboundAgents Spec.md
osnap_client/agents/PersonalAgent.py
osnap_client/agents/outbound_agent.py
osnap_client/agents/planner.py
osnap_client/core/api.py
osnap_client/core/crypt.py
osnap_client/core/osnap.py
osnap_client/main.py
osnap_client/registry/__init__.py
osnap_client/registry/agent_registry.py
osnap_client/registry/registry.py
osnap_client/registry/tool_registry.py
osnap_client/tools/__init__.py
osnap_client/tools/main.py
osnap_client/utils/ai_engines/EngineBase.py
osnap_client/utils/ai_engines/GPTConversEngine.py
osnap_client/utils/ai_engines/LanchainGoogleEngine.py
osnap_client/utils/ai_engines/__init__.py
osnap_client-0.1.0.dist-info/LICENSE
osnap_client-0.1.0.dist-info/METADATA
osnap_client-0.1.0.dist-info/WHEEL
osnap_client-0.1.0.dist-info/RECORD
