Metadata-Version: 2.1
Name: osnap-client
Version: 0.1.0
Summary: 
Author: Forrest Murray
Author-email: FMurray@gmail.com
Requires-Python: >=3.10,<4.0
Classifier: Programming Language :: Python :: 3
Classifier: Programming Language :: Python :: 3.10
Classifier: Programming Language :: Python :: 3.11
Requires-Dist: cryptography (>=40.0.2,<41.0.0)
Requires-Dist: fastapi (>=0.95.1,<0.96.0)
Requires-Dist: httpx (>=0.24.0,<0.25.0)
Requires-Dist: langchain (>=0.0.154,<0.0.155)
Requires-Dist: networkx (>=3.1,<4.0)
Requires-Dist: openai (>=0.27.5,<0.28.0)
Requires-Dist: pydantic (>=1.10.7,<2.0.0)
Requires-Dist: redis (>=4.5.4,<5.0.0)
Requires-Dist: rsa (>=4.9,<5.0)
Requires-Dist: sphinx-rtd-theme (>=1.2.0,<2.0.0)
Requires-Dist: sphinxcontrib-napoleon (>=0.7,<0.8)
Requires-Dist: uvicorn (>=0.22.0,<0.23.0)
Requires-Dist: watchfiles (>=0.19.0,<0.20.0)
Requires-Dist: websockets (>=11.0.2,<12.0.0)
